iop4-1.5.1.dist-info/licenses/LICENSE
iop4admin/__init__.py
iop4admin/apps.py
iop4admin/sites.py
iop4admin/modeladmins/aperphotresult.py
iop4admin/modeladmins/astrosource.py
iop4admin/modeladmins/epoch.py
iop4admin/modeladmins/fitfile.py
iop4admin/modeladmins/masterbias.py
iop4admin/modeladmins/masterdark.py
iop4admin/modeladmins/masterflat.py
iop4admin/modeladmins/photopolresult.py
iop4admin/modeladmins/rawfit.py
iop4admin/modeladmins/reducedfit.py
iop4admin/templates/admin/base.html
iop4admin/templates/admin/base_site.html
iop4admin/templates/iop4admin/base.custom.css
iop4admin/templates/iop4admin/singleobj.html
iop4admin/templates/iop4admin/view_astrosourcedetails.html
iop4admin/templates/iop4admin/view_epochdetails.html
iop4admin/templates/iop4admin/view_fitdetails.html
iop4admin/templates/iop4admin/view_fitviewer.html
iop4admin/templates/iop4admin/fits/change_list.html
iop4admin/templates/iop4admin/fits/textinput_filter.html
iop4admin/views/__init__.py
iop4admin/views/astrosource.py
iop4admin/views/epoch.py
iop4admin/views/fitfile.py
iop4admin/views/singleobj.py
iop4api/__init__.py
iop4api/apps.py
iop4api/filters.py
iop4api/models.py
iop4api/urls.py
iop4api/static/iop4api/base.css
iop4api/static/iop4api/gui.js
iop4api/templates/iop4api/about.html
iop4api/templates/iop4api/catalog.html
iop4api/templates/iop4api/data.html
iop4api/templates/iop4api/explore.html
iop4api/templates/iop4api/index.html
iop4api/templates/iop4api/login.html
iop4api/templates/iop4api/logs.html
iop4api/templates/iop4api/plot.html
iop4api/templates/iop4api/query.html
iop4api/views/__init__.py
iop4api/views/auth.py
iop4api/views/catalog.py
iop4api/views/data.py
iop4api/views/docs.py
iop4api/views/flag.py
iop4api/views/index.py
iop4api/views/log.py
iop4api/views/plot.py
iop4lib/__init__.py
iop4lib/_version.py
iop4lib/config.example.yaml
iop4lib/config.py
iop4lib/enums.py
iop4lib/iop4.py
iop4lib/iop4_night_summary.html
iop4lib/iop4_night_summary.py
iop4lib/version.py
iop4lib/db/__init__.py
iop4lib/db/aperphotresult.py
iop4-1.5.1.dist-info/METADATA
iop4-1.5.1.dist-info/WHEEL
iop4-1.5.1.dist-info/entry_points.txt
iop4-1.5.1.dist-info/top_level.txt
iop4-1.5.1.dist-info/RECORD
