Metadata-Version: 2.4
Name: iop4
Version: 1.5.1
Summary: A rewrite of IOP3, a pipeline to work with photometry and polarimetry of optical data from CAHA and OSN.
Author-email: Juan Escudero Pedrosa <jescudero@iaa.es>
License: BSD-3-Clause
Project-URL: repository, https://github.com/juanep97/iop4
Classifier: Programming Language :: Python :: 3
Classifier: License :: OSI Approved :: BSD License
Classifier: Operating System :: OS Independent
Requires-Python: <3.13,>=3.11
License-File: LICENSE
Requires-Dist: numpy<2,>=1.26.4
Requires-Dist: matplotlib<3.10,>=3.7.1
Requires-Dist: bokeh==3.6.0
Requires-Dist: scipy<2,>=1.10.1
Requires-Dist: astropy<6,>=5.2.2
Requires-Dist: astroquery
Requires-Dist: photutils<2,>=1.8.0
Requires-Dist: pandas
Requires-Dist: scikit-learn<2,>=1.2.2
Requires-Dist: scikit-image
Requires-Dist: coloredlogs
Requires-Dist: ipython
Requires-Dist: django<5
Requires-Dist: astrometry<5,>=4.1.2
Requires-Dist: multiprocess<1,>=0.70.14
Requires-Dist: pypandoc
Requires-Dist: termcolor
Requires-Dist: pyyaml<5.4
Requires-Dist: psutil
Requires-Dist: paramiko
Provides-Extra: test
Requires-Dist: pytest; extra == "test"
Requires-Dist: pytest-django; extra == "test"
Requires-Dist: codecov; extra == "test"
Requires-Dist: pytest-cov; extra == "test"
Provides-Extra: doc
Requires-Dist: numpydoc; extra == "doc"
Requires-Dist: sphinx; extra == "doc"
Requires-Dist: sphinx<8; python_version < "3.11" and extra == "doc"
Requires-Dist: sphinx-automodapi; extra == "doc"
Requires-Dist: sphinx-mdinclude; extra == "doc"
Requires-Dist: pydata-sphinx-theme; extra == "doc"
Requires-Dist: pydata-sphinx-theme<0.15.2; python_version < "3.11" and extra == "doc"
Requires-Dist: sphinxcontrib-bibtex; extra == "doc"
Requires-Dist: docutils>=0.20; extra == "doc"
Requires-Dist: nbsphinx; extra == "doc"
Requires-Dist: nbstripout; extra == "doc"
Requires-Dist: jupytext; extra == "doc"
Requires-Dist: ipykernel; extra == "doc"
Requires-Dist: sphinx-gallery; extra == "doc"
Requires-Dist: sphinx-gallery<=0.7.0; python_version < "3.11" and extra == "doc"
Requires-Dist: myst-nb; extra == "doc"
Provides-Extra: dev
Requires-Dist: setuptools_scm; extra == "dev"
Provides-Extra: all
Requires-Dist: iop4[dev,doc,test]; extra == "all"
Dynamic: license-file
